{
  "skills": {
    "secLabel": "Fähigkeiten<span>.</span>",
    "programmingLanguages": {
      "title": "Programmiersprachen",
      "languages": ["JavaScript", "TypeScript", "Java", "Python"]
    },
    "webTechnologies": {
      "title": "Webtechnologien",
      "technologies": ["React JS", "HTML", "CSS", "SCSS (Sass)", "Bootstrap", "jQuery"]
    },
    "backendTechnologies":{
      "title": "Backend-Technologien",
      "technologies": ["Express", "Node.js"]
    },
    "databases": {
      "title": "Datenbanken",
      "systems": ["SQL", "MySQL", "MongoDB", "Mongoose"]
    },
    "industryKnowledge": {
      "title": "Branchenwissen",
      "architecture": ["Objektorientierte Programmierung", "SOLID-Prinzipien", "Model-View-ViewModel (MVVM)", "Model-View-Controller (MVC)"]
    },
    "testing": {
      "title": "Testen",
      "test": ["Jest", "React Testing Library", "Cypress"]
    },
    "versionControl": {
      "title": "Versionskontrolle",
      "verControl": "Git"
    }
  }
}
